ff.v
module ff (
	input  clk   , // Clock
	input  clk_en, // Clock Enable
	input  rst_n , // Asynchronous reset active low
	input  d3    , // data line
	output q     , // output
	output q_
);

	wire d_,s1,r1,a,b,clk_,s2,s3,r2,r3,		clk_en_,d2,d3,q2,d;

	and(d2,d3, clk_en);
	not(clk_en_, clk_en);
	and(q2, clk_en_, q);

	or(d,d2,q2);

	not(clk_,clk);
	not(d_,d);

	nand(s1, d, clk_);
	nand(r1, d_, clk_);

	nand(s2,s1,r2);
	nand(r2,r1,s2);

	nand(s3,clk,s2);
	nand(r3,clk,r2);

	nand(q,s3,q_);
	nand(q_,r3,q);
endmodule

stimulus.v
// testbench for ff module
`timescale 1ns / 1ps
module stimulus();
	// Inputs
	reg d     ;
	reg clk   ;
	reg clk_en;
	reg rst_n = 0;


	// Outputs
	wire q;

	// Instantiate the Unit Under Test (UUT)
	ff uut (
		.clk   (clk   ),
		.clk_en(clk_en),
		.rst_n (rst_n ),
		.d3    (d    ),
		
		.q    (q     )
	);

	initial begin
		$dumpfile("ff.vcd");
		$dumpvars(21,d,clk,q,clk_en,rst_n);
	end

	initial begin
		$display("d\tclk\tq\tclk_en\trst_n\n"); //Setup Table Headers

		// Initialize Inputs
		d = 1;
		/* Make a regular pulsing clock. */
		clk = 0;
		
		clk_en = 1;
		rst_n = 0;

		#10			rst_n = 1;

		#20			rst_n = 0;

		#20			d = 0;
		#20 		d = 1;
		#20			d = 0;
		#20 		d = 1;
		#20			rst_n = 1;
		#20			d = 0;
		#20 		d = 1;
		#20			d = 0;
		#20 		d = 1;

		#40;

	end

	always #20 clk = !clk;
		
	initial begin
		$monitor("%d\t%d\t%d\t%d\t%d \n",d,clk,q,clk_en,rst_n);
	end

	initial #100 $finish;

endmodule

ff.vcd
$date
	Mon Feb 22 18:19:11 2016
$end
$version
	Icarus Verilog
$end
$timescale
	1ps
$end
$scope module stimulus $end
$var reg 1 ! d $end
$upscope $end
$scope module stimulus $end
$var reg 1 " clk $end
$upscope $end
$scope module stimulus $end
$var wire 1 # q $end
$upscope $end
$scope module stimulus $end
$var reg 1 $ clk_en $end
$upscope $end
$scope module stimulus $end
$var reg 1 % rst_n $end
$upscope $end
$enddefinitions $end
#0
$dumpvars
0%
1$
x#
0"
1!
$end
#10000
1%
#20000
1#
1"
#30000
0%
#40000
0"
#50000
0!
#60000
0#
1"
#70000
1!
#80000
0"
#90000
0!
