ff.v
module ff (
	clk   , // Clock
	clk_en, // Clock Enable
	rst_n , // Asynchronous reset active high
	d3    , // data line
	q     , // output
	q_
);
	input wire clk, clk_en, rst_n, d3;
	output reg q, q_;
	always @(posedge clk,  negedge clk) begin
		if (clk_en & ~rst_n) begin
			q <= d3;
			q_ <= ~d3;
		end else begin
			q <= 1'b0;
			q_ <= 1'b0;
		end
	end	
endmodule

counter.v
// testbench for counter module
`timescale 1ns / 1ps
module stimulus();
	// Inputs
	reg rst_n =0;
	initial begin 
		$dumpfile("test.vcd");
		$dumpvars(0,test);

		// changing values here.

		%20 d=1;

	end

	reg clk = 0;
	always #1 clk = !clk;
	reg clk_en = 1;

	

	// Outputs
	wire q_1,q_2,d1toq_1,q1toclk2,q_2tod2,q2;
	not(q_1,q1);
	not(q_2,q2);
	// Instantiate the Unit Under Test (UUT)
	ff ff1 (
		.clk   (clk   ),
		.clk_en(clk_en),
		.rst_n (rst_n ),
		.d3    (d1toq_1),    ),
		
		.q     (q1toclk2     )
	);

	ff ff1 (
		.clk   (q1toclk2   ),
		.clk_en(clk_en),
		.rst_n (rst_n ),
		.d3    (q_2tod2),    ),
		
		.q     (q2     )
	);

	initial begin
		$dumpfile("ff.vcd");
		$dumpvars(21,q1toclk2,q2,clk);
	end

	initial begin
		$display("q1\tq2\tclk\n"); //Setup Table Headers

		
		// 	time delay	changes
		
		#4		 	 = 1;
		#10	 		clk = 0;
		#20			d = 0;
		#10		 	clk = 1;
		#10	 		clk = 0;

		#40;

	end

	initial begin
		$monitor("%d\t%d\t%d\t%d \n",d,clk,q,clk_en);
	end

endmodule

ff.vcd
$date
	Wed Feb 24 15:04:40 2016
$end
$version
	Icarus Verilog
$end
$timescale
	1ps
$end
$scope module stimulus $end
$var reg 1 ! d $end
$upscope $end
$scope module stimulus $end
$var reg 1 " clk $end
$upscope $end
$scope module stimulus $end
$var wire 1 # q $end
$upscope $end
$scope module stimulus $end
$var reg 1 $ clk_en $end
$upscope $end
$scope module stimulus $end
$var reg 1 % rst_n $end
$upscope $end
$enddefinitions $end
#0
$dumpvars
0%
1$
x#
0"
1!
$end
#1000
1#
1"
#2000
0"
#3000
1"
#4000
0"
#5000
1"
#6000
0"
#7000
1"
#8000
0"
#9000
1"
#10000
0"
#11000
1"
#12000
0"
#13000
1"
#14000
0"
#15000
1"
#16000
0"
#17000
1"
#18000
0"
#19000
1"
#20000
0"
1%
#21000
1"
#22000
0"
#23000
1"
#24000
0"
#25000
1"
0!
#26000
0"
#27000
0#
1"
#28000
0"
#29000
1"
#30000
0"
1!
#31000
1#
1"
#32000
0"
#33000
1"
#34000
0"
#35000
1"
0!
#36000
0"
#37000
0#
1"
#38000
0"
#39000
1"
#40000
0"
#41000
1"
#42000
0"
#43000
1"
#44000
0"
#45000
1"
#46000
0"
#47000
1"
#48000
0"
#49000
1"
#50000
0"
#51000
1"
#52000
0"
#53000
1"
#54000
0"
#55000
1"
1!
#56000
0"
#57000
1#
1"
#58000
0"
#59000
1"
#60000
0"
#61000
1"
#62000
0"
#63000
1"
#64000
0"
#65000
1"
#66000
0"
#67000
1"
#68000
0"
#69000
1"
#70000
0"
#71000
1"
#72000
0"
#73000
1"
#74000
0"
#75000
1"
0%
#76000
0"
#77000
1"
#78000
0"
#79000
1"
#80000
0"
#81000
1"
#82000
0"
#83000
1"
#84000
0"
#85000
1"
#86000
0"
#87000
1"
#88000
0"
#89000
1"
#90000
0"
#91000
1"
#92000
0"
#93000
1"
#94000
0"
#95000
1"
0!
#96000
0"
#97000
0#
1"
